easyaudit/__init__.py
easyaudit/admin.py
easyaudit/admin_helpers.py
easyaudit/apps.py
easyaudit/backends.py
easyaudit/crudhistory_admin_mixin.py
easyaudit/models.py
easyaudit/settings.py
easyaudit/utils.py
easyaudit/views.py
easyaudit/middleware/__init__.py
easyaudit/middleware/easyaudit.py
easyaudit/migrations/0001_initial.py
easyaudit/migrations/0002_auto_20170125_0759.py
easyaudit/migrations/0003_auto_20170228_1505.py
easyaudit/migrations/0004_auto_20170620_1354.py
easyaudit/migrations/0005_auto_20170713_1155.py
easyaudit/migrations/0006_auto_20171018_1242.py
easyaudit/migrations/0007_auto_20180105_0838.py
easyaudit/migrations/0008_auto_20180220_1908.py
easyaudit/migrations/0009_auto_20180314_2225.py
easyaudit/migrations/0010_repr_text.py
easyaudit/migrations/0011_auto_20181101_1339.py
easyaudit/migrations/0012_auto_20181018_0012.py
easyaudit/migrations/0013_auto_20190723_0126.py
easyaudit/migrations/0014_auto_20200513_0008.py
easyaudit/migrations/0015_auto_20201019_1217.py
easyaudit/migrations/0016_alter_crudevent_event_type.py
easyaudit/migrations/0017_alter_requestevent_datetime.py
easyaudit/migrations/__init__.py
easyaudit/signals/__init__.py
easyaudit/signals/auth_signals.py
easyaudit/signals/model_signals.py
easyaudit/signals/request_signals.py
easyaudit/templates/admin/easyaudit/change_list.html
easyaudit/templates/admin/easyaudit/purge_confirmation.html
django_easy_audit-1.3.6.dist-info/LICENSE
django_easy_audit-1.3.6.dist-info/METADATA
django_easy_audit-1.3.6.dist-info/WHEEL
django_easy_audit-1.3.6.dist-info/top_level.txt
django_easy_audit-1.3.6.dist-info/RECORD
